datvtn_kit/__init__.py
datvtn_kit/common/__init__.py
datvtn_kit/common/data.py
datvtn_kit/common/face_align.py
datvtn_kit/common/image.py
datvtn_kit/common/misc.py
datvtn_kit/common/plot.py
datvtn_kit/config_parsing/__init__.py
datvtn_kit/config_parsing/utils.py
datvtn_kit/data_processing/__init__.py
datvtn_kit/metrics/__init__.py
datvtn_kit/metrics/coco_file_eval.py
datvtn_kit/utils/__init__.py
datvtn_kit/utils/box_utils.py
datvtn_kit/utils/general_utils.py
datvtn_kit/utils/geometry_utils.py
datvtn_kit/utils/image_utils.py
datvtn_kit/utils/inpainting_utils.py
datvtn_kit/utils/mask_utils.py
datvtn_kit/utils/tabular_utils.py
datvtn_kit-0.0.3.dist-info/METADATA
datvtn_kit-0.0.3.dist-info/WHEEL
datvtn_kit-0.0.3.dist-info/top_level.txt
datvtn_kit-0.0.3.dist-info/RECORD
